cph_classification/__init__.py
cph_classification/cli.py
cph_classification/classification/__init__.py
cph_classification/classification/callbacks.py
cph_classification/classification/cli.py
cph_classification/classification/datamodule.py
cph_classification/classification/dataset.py
cph_classification/classification/main.py
cph_classification/classification/mainfittest.py
cph_classification/classification/modelfactory.py
cph_classification/classification/modelmodule.py
cph_classification-0.2.1.dist-info/licenses/LICENSE
cph_classification-0.2.1.dist-info/METADATA
cph_classification-0.2.1.dist-info/WHEEL
cph_classification-0.2.1.dist-info/entry_points.txt
cph_classification-0.2.1.dist-info/top_level.txt
cph_classification-0.2.1.dist-info/RECORD
